qolproximity/__init__.py
qolproximity/qolproximity.py
qolproximity-1.4.dist-info/LICENSE.txt
qolproximity-1.4.dist-info/METADATA
qolproximity-1.4.dist-info/WHEEL
qolproximity-1.4.dist-info/top_level.txt
qolproximity-1.4.dist-info/RECORD
