Metadata-Version: 2.1
Name: qolproximity
Version: 1.4
Summary: library code execute various proximity analyses using ArcPy for qol proximity analyses
Home-page: https://github.com/ProvidenceAdu/qolproximity
Author: Providence Adu,Ph.D.
Author-email: padu@charlotte.edu
License-File: LICENSE.txt
Requires-Dist: pandas >=1.0.0
